wepy/__about__.py
wepy/__init__.py
wepy/__main__.py
wepy/_print_version.py
wepy/hdf5.py
wepy/sim_manager.py
wepy/walker.py
wepy/wepy.code-workspace
wepy/analysis/__init__.py
wepy/analysis/contig_tree.py
wepy/analysis/distributed.py
wepy/analysis/network.py
wepy/analysis/parents.py
wepy/analysis/profiles.py
wepy/analysis/rates.py
wepy/analysis/transitions.py
wepy/analysis/network_layouts/__init__.py
wepy/analysis/network_layouts/layout.py
wepy/analysis/network_layouts/layout_graph.py
wepy/analysis/network_layouts/tree.py
wepy/boundary_conditions/__init__.py
wepy/boundary_conditions/boundary.py
wepy/boundary_conditions/randomwalk.py
wepy/boundary_conditions/receptor.py
wepy/boundary_conditions/unbinding.py
wepy/orchestration/__init__.py
wepy/orchestration/cli.py
wepy/orchestration/configuration.py
wepy/orchestration/orchestrator.py
wepy/orchestration/snapshot.py
wepy/reporter/__init__.py
wepy/reporter/dashboard.py
wepy/reporter/hdf5.py
wepy/reporter/openmm.py
wepy/reporter/reporter.py
wepy/reporter/restree.py
wepy/reporter/walker.py
wepy/reporter/walker_pkl.py
wepy/reporter/receptor/__init__.py
wepy/reporter/receptor/dashboard.py
wepy/reporter/revo/__init__.py
wepy/reporter/revo/dashboard.py
wepy/reporter/wexplore/__init__.py
wepy/reporter/wexplore/dashboard.py
wepy/resampling/__init__.py
wepy/resampling/decisions/__init__.py
wepy/resampling/decisions/clone_merge.py
wepy/resampling/decisions/decision.py
wepy/resampling/distances/__init__.py
wepy/resampling/distances/distance.py
wepy/resampling/distances/randomwalk.py
wepy/resampling/distances/receptor.py
wepy/resampling/resamplers/__init__.py
wepy/resampling/resamplers/clone_merge.py
wepy/resampling/resamplers/resampler.py
wepy/resampling/resamplers/revo.py
wepy/resampling/resamplers/wexplore.py
wepy/runners/__init__.py
wepy/runners/openmm.py
wepy/runners/randomwalk.py
wepy/runners/runner.py
wepy/util/__init__.py
wepy/util/json_top.py
wepy/util/kv.py
wepy/util/mdtraj.py
wepy/util/test_system_builder.py
wepy-1.2.dist-info/METADATA
wepy-1.2.dist-info/WHEEL
wepy-1.2.dist-info/entry_points.txt
wepy-1.2.dist-info/licenses/AUTHORS.org
wepy-1.2.dist-info/licenses/LICENSE
wepy-1.2.dist-info/RECORD
