Metadata-Version: 2.4
Name: wepy
Version: 1.2
Summary: Weighted Ensemble Framework
Project-URL: Documentation, https://adicksonlab.github.io/wepy/index.html
Project-URL: Source, https://github.com/ADicksonLab/wepy
Project-URL: Issues, https://github.com/ADicksonLab/wepy/issues
Author: Tom Dixon, Robert Hall, Nicole Roussey
Author-email: Samuel Lotz <salotz@salotz.info>, Alex Dickson <alexrd@msu.edu>
License-Expression: MIT
License-File: AUTHORS.org
License-File: LICENSE
Classifier: License :: OSI Approved :: MIT License
Classifier: Programming Language :: Python :: 3
Classifier: Topic :: Utilities
Requires-Dist: click
Requires-Dist: dill
Requires-Dist: geomm>=0.3
Requires-Dist: h5py>=3
Requires-Dist: jinja2
Requires-Dist: multiprocessing-logging
Requires-Dist: networkx
Requires-Dist: numpy
Requires-Dist: pandas
Requires-Dist: pint
Requires-Dist: scipy
Requires-Dist: tabulate
Provides-Extra: distributed
Requires-Dist: dask[bag]; extra == 'distributed'
Provides-Extra: graphics
Requires-Dist: matplotlib; extra == 'graphics'
Requires-Dist: pillow>=10.0.1; extra == 'graphics'
Provides-Extra: md
Requires-Dist: mdtraj; extra == 'md'
Requires-Dist: openmm-systems==0.0.0; extra == 'md'
Provides-Extra: prometheus
Requires-Dist: prometheus-client; extra == 'prometheus'
Requires-Dist: pympler; extra == 'prometheus'
